aws_quota/__init__.py
aws_quota/cli.py
aws_quota/exceptions.py
aws_quota/prometheus.py
aws_quota/utils.py
aws_quota/check/__init__.py
aws_quota/check/appmesh.py
aws_quota/check/autoscaling.py
aws_quota/check/cloudformation.py
aws_quota/check/dynamodb.py
aws_quota/check/ebs.py
aws_quota/check/ec2.py
aws_quota/check/ecs.py
aws_quota/check/eks.py
aws_quota/check/elasticbeanstalk.py
aws_quota/check/elb.py
aws_quota/check/iam.py
aws_quota/check/lambdas.py
aws_quota/check/quota_check.py
aws_quota/check/rds.py
aws_quota/check/route53.py
aws_quota/check/route53resolver.py
aws_quota/check/s3.py
aws_quota/check/secretsmanager.py
aws_quota/check/ses.py
aws_quota/check/sns.py
aws_quota/check/vpc.py
aws_quota_checker-1.12.0.dist-info/LICENSE
aws_quota_checker-1.12.0.dist-info/METADATA
aws_quota_checker-1.12.0.dist-info/WHEEL
aws_quota_checker-1.12.0.dist-info/entry_points.txt
aws_quota_checker-1.12.0.dist-info/top_level.txt
aws_quota_checker-1.12.0.dist-info/RECORD
