Metadata-Version: 2.1
Name: aws-quota-checker
Version: 1.12.0
Summary: A CLI tool that checks your AWS quota utilization
Home-page: UNKNOWN
License: UNKNOWN
Platform: UNKNOWN
Requires-Dist: boto3
Requires-Dist: click
Requires-Dist: tabulate
Requires-Dist: cachetools
Provides-Extra: dev
Requires-Dist: autopep8 ; extra == 'dev'
Requires-Dist: pylint ; extra == 'dev'
Requires-Dist: wheel ; extra == 'dev'
Requires-Dist: keepachangelog ; extra == 'dev'
Provides-Extra: prometheus
Requires-Dist: prometheus-client ; extra == 'prometheus'
